docketanalyzer_core/__init__.py
docketanalyzer_core/__main__.py
docketanalyzer_core/registry.py
docketanalyzer_core/utils.py
docketanalyzer_core/choices/__init__.py
docketanalyzer_core/choices/choice.py
docketanalyzer_core/choices/court.py
docketanalyzer_core/choices/docket.py
docketanalyzer_core/choices/idb.py
docketanalyzer_core/choices/judge.py
docketanalyzer_core/choices/nature_suit.py
docketanalyzer_core/choices/party.py
docketanalyzer_core/cli/__init__.py
docketanalyzer_core/cli/configure.py
docketanalyzer_core/cli/open.py
docketanalyzer_core/cli/sync.py
docketanalyzer_core/cli/dev/__init__.py
docketanalyzer_core/cli/dev/build.py
docketanalyzer_core/config/__init__.py
docketanalyzer_core/config/config.py
docketanalyzer_core/config/env.py
docketanalyzer_core/docket/__init__.py
docketanalyzer_core/docket/docket_batch.py
docketanalyzer_core/docket/docket_index.py
docketanalyzer_core/docket/docket_manager.py
docketanalyzer_core/services/__init__.py
docketanalyzer_core/services/elastic.py
docketanalyzer_core/services/psql.py
docketanalyzer_core/services/redis.py
docketanalyzer_core/services/s3.py
docketanalyzer_core-0.1.11.dist-info/METADATA
docketanalyzer_core-0.1.11.dist-info/WHEEL
docketanalyzer_core-0.1.11.dist-info/licenses/LICENSE
docketanalyzer_core-0.1.11.dist-info/RECORD
