Metadata-Version: 2.4
Name: docketanalyzer-core
Version: 0.1.11
Summary: Docket Analyzer Core Utilities
Author: Nathan Dahlberg
License-File: LICENSE
Requires-Python: >=3.10
Requires-Dist: awscli>=1.38.11
Requires-Dist: boto3>=1.37.11
Requires-Dist: click>=8.0.0
Requires-Dist: elasticsearch>=8.17.2
Requires-Dist: pandas>=2.2.3
Requires-Dist: pathlib>=1.0.1
Requires-Dist: peewee>=3.17.9
Requires-Dist: psycopg2-binary>=2.9.10
Requires-Dist: python-dotenv>=1.0.0
Requires-Dist: redis>=5.0.1
Requires-Dist: regex>=2.5.148
Requires-Dist: requests>=2.32.3
Requires-Dist: simplejson>=3.19.3
Requires-Dist: tqdm>=4.66.2
Provides-Extra: dev
Requires-Dist: build>=1.0.0; extra == 'dev'
Requires-Dist: pytest-cov>=4.0; extra == 'dev'
Requires-Dist: pytest>=7.0; extra == 'dev'
Requires-Dist: ruff>=0.9.10; extra == 'dev'
Requires-Dist: tomli-w>=1.2.0; extra == 'dev'
Requires-Dist: tomli>=2.0.0; extra == 'dev'
Requires-Dist: twine>=4.0.0; extra == 'dev'
